{
    "id": "760d526db24aa9",
    "is2h": false,
    "name": "Marika's Hammer, l2, dps calc.",
    "sets": {
        "weapons": [
            {
                "name": "Default",
                "active": true
            }
        ],
        "talismans": [
            {
                "name": "Default",
                "active": true
            }
        ],
        "protectors": [
            {
                "name": "Default",
                "active": true
            }
        ]
    },
    "tags": [
        "Quality",
        "PvE",
        "DLC: SotE"
    ],
    "isPvE": true,
    "items": {
        "ammo": {
            "slots": []
        },
        "tools": {
            "slots": [],
            "sorting": {
                "method": "acquisition",
                "direction": "asc"
            }
        },
        "flasks": {
            "level": 12,
            "total": 14,
            "crimson": 10,
            "cerulean": 4
        },
        "crystalTears": [
            "Bloodsucking Cracked Tear",
            "Holy-Shrouding Cracked Tear"
        ]
    },
    "stats": {
        "rl": 125,
        "arc": 7,
        "dex": 18,
        "fth": 33,
        "int": 9,
        "mnd": 10,
        "str": 56,
        "vig": 60,
        "vit": 11
    },
    "views": {
        "overview": "build-planner",
        "item-view/left": "Crystal Tears",
        "item-view/right": "Equipment",
        "weapons-view/left": "Edit"
    },
    "spells": {
        "slots": [
            {
                "name": "Howl of Shabriri",
                "order": 0
            }
        ]
    },
    "computed": {
        "maxFP": 78,
        "poise": {
            "original": 31
        },
        "runes": {
            "total": 3979025,
            "toNextLevel": 102838
        },
        "defenses": {
            "fire": 187,
            "holy": 141,
            "magic": 145,
            "slash": 154,
            "pierce": 154,
            "strike": 154,
            "physical": 154,
            "lightning": 127
        },
        "maxHealth": 1900,
        "absorption": {
            "fire": 8.673271931555204,
            "holy": 7.413082762240009,
            "magic": 7.413082762240009,
            "slash": 1.5463216792000023,
            "pierce": 0.8121848614278449,
            "strike": -1.2031083884268767,
            "physical": 0.17762025643265344,
            "lightning": 6.82674539152962
        },
        "maxStamina": 97,
        "resistances": {
            "focus": 187,
            "immunity": 238,
            "vitality": 194,
            "robustness": 232
        },
        "maxEquipLoad": 49.76470588
    },
    "inventory": {
        "slots": [
            {
                "name": "Marika's Hammer",
                "order": 0,
                "upgrade": null,
                "equipSet": [
                    0
                ],
                "infusion": "Standard",
                "weaponArt": null,
                "equipIndex": 0
            },
            {
                "name": "Dagger",
                "order": 1,
                "upgrade": 0,
                "equipSet": [
                    3
                ],
                "infusion": "Standard",
                "weaponArt": "Sacred Order",
                "equipIndex": 3
            },
            {
                "name": "Madding Hand",
                "order": 2,
                "upgrade": 0,
                "equipSet": [
                    4
                ],
                "infusion": "Standard",
                "weaponArt": null,
                "equipIndex": 4
            }
        ],
        "sorting": {
            "method": "acquisition",
            "direction": "asc"
        }
    },
    "talismans": {
        "slots": [
            {
                "name": "Shard of Alexander",
                "order": 0,
                "equipSet": [
                    0
                ],
                "equipIndex": 0
            },
            {
                "name": "Sacred Scorpion Charm",
                "order": 1,
                "equipSet": [
                    1
                ],
                "equipIndex": 1
            },
            {
                "name": "Blade of Mercy",
                "order": 2,
                "equipSet": [
                    2
                ],
                "equipIndex": 2
            },
            {
                "name": "Aged One's Exultation",
                "order": 3,
                "equipSet": [
                    3
                ],
                "equipIndex": 3
            }
        ],
        "sorting": {
            "method": "acquisition",
            "direction": "asc"
        }
    },
    "conditions": {
        "forEffects": [],
        "crystalTears": false
    },
    "protectors": {
        "arms": {
            "slots": [
                {
                    "name": "Rakshasa Gauntlets",
                    "order": 0,
                    "equipSet": [
                        1
                    ],
                    "equipIndex": 1
                }
            ],
            "sorting": {
                "method": "acquisition",
                "direction": "asc"
            }
        },
        "body": {
            "slots": [],
            "sorting": {
                "method": "acquisition",
                "direction": "asc"
            }
        },
        "head": {
            "slots": [
                {
                    "name": "Omensmirk Mask",
                    "order": 0
                },
                {
                    "name": "Rakshasa Helm",
                    "order": 1,
                    "equipSet": [
                        1
                    ],
                    "equipIndex": 1
                }
            ],
            "sorting": {
                "method": "acquisition",
                "direction": "asc"
            }
        },
        "legs": {
            "slots": [
                {
                    "name": "Rakshasa Greaves",
                    "order": 0,
                    "equipSet": [
                        1
                    ],
                    "equipIndex": 1
                }
            ],
            "sorting": {
                "method": "acquisition",
                "direction": "asc"
            }
        }
    },
    "weaponUpgrade": 25,
    "characterClass": "Vagabond"
}