{
    "id": "20e23c669d482e",
    "is2h": true,
    "name": "153\u529b\u53f7",
    "sets": {
        "weapons": [
            {
                "name": "Default",
                "active": true
            }
        ],
        "talismans": [
            {
                "name": "Default",
                "active": true
            }
        ],
        "protectors": [
            {
                "name": "Default",
                "active": true
            }
        ]
    },
    "tags": [
        "Invasions",
        "Strength",
        "DLC: SotE"
    ],
    "isPvE": false,
    "items": {
        "ammo": {
            "slots": []
        },
        "tools": {
            "slots": [],
            "sorting": {
                "method": "acquisition",
                "direction": "asc"
            }
        },
        "flasks": {
            "level": 12,
            "total": 14,
            "crimson": 10,
            "cerulean": 4
        },
        "crystalTears": [
            null,
            null
        ]
    },
    "stats": {
        "rl": 153,
        "arc": 7,
        "dex": 18,
        "fth": 9,
        "int": 18,
        "mnd": 10,
        "str": 75,
        "vig": 55,
        "vit": 40
    },
    "views": {
        "overview": "swappa",
        "weapons-view/left": "Picker"
    },
    "spells": {
        "slots": []
    },
    "computed": {
        "maxFP": 78,
        "poise": {
            "original": 83
        },
        "runes": {
            "total": 7574897,
            "toNextLevel": 163467
        },
        "defenses": {
            "fire": 188,
            "holy": 147,
            "magic": 169,
            "slash": 166,
            "pierce": 166,
            "strike": 166,
            "physical": 166,
            "lightning": 133
        },
        "maxHealth": 1850.28,
        "absorption": {
            "fire": 27.558946955199993,
            "holy": 25.2633300184,
            "magic": 25.02301065400001,
            "slash": 34.262767313599994,
            "pierce": 32.64174643480001,
            "strike": 30.09631042880001,
            "physical": 35.10790341759999,
            "lightning": 24.805691200000012
        },
        "maxStamina": 149.1,
        "resistances": {
            "focus": 232,
            "immunity": 346,
            "vitality": 260,
            "robustness": 384
        },
        "maxEquipLoad": 94.99072559
    },
    "inventory": {
        "slots": [
            {
                "name": "Pata",
                "order": 0,
                "upgrade": null,
                "infusion": "Heavy",
                "weaponArt": "Endure"
            },
            {
                "name": "Pata",
                "order": 1,
                "upgrade": null,
                "infusion": "Heavy",
                "weaponArt": "Endure"
            },
            {
                "name": "Pata",
                "order": 2,
                "upgrade": null,
                "infusion": "Heavy",
                "weaponArt": "Endure"
            },
            {
                "name": "Pata",
                "order": 3,
                "upgrade": null,
                "infusion": "Heavy",
                "weaponArt": "Endure"
            },
            {
                "name": "Pata",
                "order": 4,
                "upgrade": null,
                "infusion": "Heavy",
                "weaponArt": "Endure"
            },
            {
                "name": "Star Fist",
                "order": 5,
                "upgrade": null,
                "infusion": "Heavy",
                "weaponArt": "Endure"
            },
            {
                "name": "Starscourge Greatsword",
                "order": 6,
                "upgrade": null,
                "infusion": "Standard",
                "weaponArt": null
            },
            {
                "name": "Gazing Finger",
                "order": 7,
                "upgrade": null,
                "infusion": "Standard",
                "weaponArt": null
            },
            {
                "name": "Star Fist",
                "order": 8,
                "upgrade": null,
                "infusion": "Heavy",
                "weaponArt": "Endure"
            },
            {
                "name": "Godskin Stitcher",
                "order": 9,
                "upgrade": null,
                "infusion": "Heavy",
                "weaponArt": "Raptor of the Mists"
            },
            {
                "name": "Great Club",
                "order": 10,
                "upgrade": null,
                "infusion": "Standard",
                "weaponArt": null
            },
            {
                "name": "Commander's Standard",
                "order": 11,
                "upgrade": null,
                "infusion": "Standard",
                "weaponArt": null
            },
            {
                "name": "Godskin Stitcher",
                "order": 12,
                "upgrade": null,
                "infusion": "Heavy",
                "weaponArt": "Raptor of the Mists"
            },
            {
                "name": "Executioner's Greataxe",
                "order": 13,
                "upgrade": null,
                "infusion": "Heavy",
                "weaponArt": "Raptor of the Mists"
            },
            {
                "name": "Commander's Standard",
                "order": 14,
                "upgrade": null,
                "infusion": "Standard",
                "weaponArt": null
            },
            {
                "name": "Golem Greatbow",
                "order": 15,
                "upgrade": null,
                "infusion": "Standard",
                "weaponArt": null
            },
            {
                "name": "Zamor Curved Sword",
                "order": 16,
                "upgrade": null,
                "infusion": "Standard",
                "weaponArt": null
            },
            {
                "name": "Igon's Greatbow",
                "order": 17,
                "upgrade": null,
                "infusion": "Standard",
                "weaponArt": "Rain of Arrows"
            },
            {
                "name": "Golem Greatbow",
                "order": 18,
                "upgrade": null,
                "infusion": "Standard",
                "weaponArt": null
            },
            {
                "name": "Zamor Curved Sword",
                "order": 19,
                "upgrade": null,
                "infusion": "Standard",
                "weaponArt": null
            },
            {
                "name": "Zweihander",
                "order": 20,
                "upgrade": null,
                "infusion": "Cold",
                "weaponArt": "Waves of Darkness"
            },
            {
                "name": "Red Bear's Claw",
                "order": 21,
                "upgrade": null,
                "infusion": "Standard",
                "weaponArt": null
            },
            {
                "name": "Smithscript Shield",
                "order": 22,
                "upgrade": null,
                "infusion": "Standard",
                "weaponArt": null
            },
            {
                "name": "Zweihander",
                "order": 23,
                "upgrade": null,
                "infusion": "Cold",
                "weaponArt": "Waves of Darkness"
            },
            {
                "name": "Backhand Blade",
                "order": 24,
                "upgrade": null,
                "infusion": "Heavy",
                "weaponArt": "Blind Spot"
            },
            {
                "name": "Cleanrot Knight's Sword",
                "order": 25,
                "upgrade": null,
                "infusion": "Heavy",
                "weaponArt": "Assassin's Gambit"
            },
            {
                "name": "Ruins Greatsword",
                "order": 26,
                "upgrade": null,
                "infusion": "Standard",
                "weaponArt": null
            },
            {
                "name": "Icon Shield",
                "order": 27,
                "upgrade": null,
                "infusion": "Standard",
                "weaponArt": null
            },
            {
                "name": "Bone Bow",
                "order": 28,
                "upgrade": null,
                "infusion": "Standard",
                "weaponArt": null
            },
            {
                "name": "Moonrithyll's Knight Sword",
                "order": 29,
                "upgrade": null,
                "infusion": "Standard",
                "weaponArt": null
            },
            {
                "name": "Grafted Blade Greatsword",
                "order": 30,
                "upgrade": null,
                "infusion": "Standard",
                "weaponArt": null
            },
            {
                "name": "Grafted Blade Greatsword",
                "order": 31,
                "upgrade": null,
                "infusion": "Standard",
                "weaponArt": null
            },
            {
                "name": "Grafted Blade Greatsword",
                "order": 32,
                "upgrade": null,
                "infusion": "Standard",
                "weaponArt": null
            },
            {
                "name": "Grafted Blade Greatsword",
                "order": 33,
                "upgrade": null,
                "infusion": "Standard",
                "weaponArt": null
            },
            {
                "name": "Grafted Blade Greatsword",
                "order": 34,
                "upgrade": null,
                "infusion": "Standard",
                "weaponArt": null
            },
            {
                "name": "Grafted Blade Greatsword",
                "order": 35,
                "upgrade": null,
                "infusion": "Standard",
                "weaponArt": null
            },
            {
                "name": "Grafted Blade Greatsword",
                "order": 36,
                "upgrade": null,
                "infusion": "Standard",
                "weaponArt": null
            },
            {
                "name": "Grafted Blade Greatsword",
                "order": 37,
                "upgrade": null,
                "infusion": "Standard",
                "weaponArt": null
            },
            {
                "name": "Grafted Blade Greatsword",
                "order": 38,
                "upgrade": null,
                "infusion": "Standard",
                "weaponArt": null
            },
            {
                "name": "Grafted Blade Greatsword",
                "order": 39,
                "upgrade": null,
                "infusion": "Standard",
                "weaponArt": null
            },
            {
                "name": "Grafted Blade Greatsword",
                "order": 40,
                "upgrade": null,
                "infusion": "Standard",
                "weaponArt": null
            },
            {
                "name": "Grafted Blade Greatsword",
                "order": 41,
                "upgrade": null,
                "infusion": "Standard",
                "weaponArt": null
            },
            {
                "name": "Grafted Blade Greatsword",
                "order": 42,
                "upgrade": null,
                "infusion": "Standard",
                "weaponArt": null
            },
            {
                "name": "Grafted Blade Greatsword",
                "order": 43,
                "upgrade": null,
                "infusion": "Standard",
                "weaponArt": null
            },
            {
                "name": "Grafted Blade Greatsword",
                "order": 44,
                "upgrade": null,
                "infusion": "Standard",
                "weaponArt": null
            },
            {
                "name": "Grafted Blade Greatsword",
                "order": 45,
                "upgrade": null,
                "infusion": "Standard",
                "weaponArt": null
            },
            {
                "name": "Grafted Blade Greatsword",
                "order": 46,
                "upgrade": null,
                "infusion": "Standard",
                "weaponArt": null
            },
            {
                "name": "Grafted Blade Greatsword",
                "order": 47,
                "upgrade": null,
                "infusion": "Standard",
                "weaponArt": null
            },
            {
                "name": "Grafted Blade Greatsword",
                "order": 48,
                "upgrade": null,
                "infusion": "Standard",
                "weaponArt": null
            },
            {
                "name": "Grafted Blade Greatsword",
                "order": 49,
                "upgrade": null,
                "infusion": "Standard",
                "weaponArt": null
            },
            {
                "name": "Grafted Blade Greatsword",
                "order": 50,
                "upgrade": null,
                "infusion": "Standard",
                "weaponArt": null
            },
            {
                "name": "Grafted Blade Greatsword",
                "order": 51,
                "upgrade": null,
                "infusion": "Standard",
                "weaponArt": null
            },
            {
                "name": "Grafted Blade Greatsword",
                "order": 52,
                "upgrade": null,
                "infusion": "Standard",
                "weaponArt": null
            },
            {
                "name": "Grafted Blade Greatsword",
                "order": 53,
                "upgrade": null,
                "infusion": "Standard",
                "weaponArt": null
            },
            {
                "name": "Grafted Blade Greatsword",
                "order": 54,
                "upgrade": null,
                "infusion": "Standard",
                "weaponArt": null
            },
            {
                "name": "Cleanrot Knight's Sword",
                "order": 55,
                "upgrade": null,
                "infusion": "Heavy",
                "weaponArt": "Bloodhound's Step"
            },
            {
                "name": "Cleanrot Knight's Sword",
                "order": 56,
                "upgrade": null,
                "infusion": "Heavy",
                "weaponArt": "Bloodhound's Step"
            },
            {
                "name": "Cleanrot Knight's Sword",
                "order": 57,
                "upgrade": null,
                "infusion": "Heavy",
                "weaponArt": "Bloodhound's Step"
            },
            {
                "name": "Cleanrot Knight's Sword",
                "order": 58,
                "upgrade": null,
                "equipSet": [
                    0
                ],
                "infusion": "Heavy",
                "weaponArt": "Bloodhound's Step",
                "equipIndex": 0
            },
            {
                "name": "Cleanrot Knight's Sword",
                "order": 59,
                "upgrade": null,
                "infusion": "Heavy",
                "weaponArt": "Bloodhound's Step"
            },
            {
                "name": "Cleanrot Knight's Sword",
                "order": 60,
                "upgrade": null,
                "infusion": "Heavy",
                "weaponArt": "Bloodhound's Step"
            },
            {
                "name": "Cleanrot Knight's Sword",
                "order": 61,
                "upgrade": null,
                "infusion": "Heavy",
                "weaponArt": "Bloodhound's Step"
            },
            {
                "name": "Cleanrot Knight's Sword",
                "order": 62,
                "upgrade": null,
                "infusion": "Heavy",
                "weaponArt": "Bloodhound's Step"
            },
            {
                "name": "Cleanrot Knight's Sword",
                "order": 63,
                "upgrade": null,
                "infusion": "Heavy",
                "weaponArt": "Bloodhound's Step"
            },
            {
                "name": "Cleanrot Knight's Sword",
                "order": 64,
                "upgrade": null,
                "infusion": "Heavy",
                "weaponArt": "Bloodhound's Step"
            },
            {
                "name": "Cleanrot Knight's Sword",
                "order": 65,
                "upgrade": null,
                "infusion": "Heavy",
                "weaponArt": "Bloodhound's Step"
            },
            {
                "name": "Cleanrot Knight's Sword",
                "order": 66,
                "upgrade": null,
                "infusion": "Heavy",
                "weaponArt": "Bloodhound's Step"
            },
            {
                "name": "Cleanrot Knight's Sword",
                "order": 67,
                "upgrade": null,
                "infusion": "Heavy",
                "weaponArt": "Bloodhound's Step"
            },
            {
                "name": "Cleanrot Knight's Sword",
                "order": 68,
                "upgrade": null,
                "infusion": "Heavy",
                "weaponArt": "Bloodhound's Step"
            },
            {
                "name": "Cleanrot Knight's Sword",
                "order": 69,
                "upgrade": null,
                "infusion": "Heavy",
                "weaponArt": "Bloodhound's Step"
            },
            {
                "name": "Cleanrot Knight's Sword",
                "order": 70,
                "upgrade": null,
                "infusion": "Heavy",
                "weaponArt": "Bloodhound's Step"
            },
            {
                "name": "Cleanrot Knight's Sword",
                "order": 71,
                "upgrade": null,
                "infusion": "Heavy",
                "weaponArt": "Bloodhound's Step"
            },
            {
                "name": "Cleanrot Knight's Sword",
                "order": 72,
                "upgrade": null,
                "infusion": "Heavy",
                "weaponArt": "Bloodhound's Step"
            },
            {
                "name": "Cleanrot Knight's Sword",
                "order": 73,
                "upgrade": null,
                "infusion": "Heavy",
                "weaponArt": "Bloodhound's Step"
            },
            {
                "name": "Cleanrot Knight's Sword",
                "order": 74,
                "upgrade": null,
                "infusion": "Heavy",
                "weaponArt": "Bloodhound's Step"
            },
            {
                "name": "Cleanrot Knight's Sword",
                "order": 75,
                "upgrade": null,
                "infusion": "Heavy",
                "weaponArt": "Bloodhound's Step"
            },
            {
                "name": "Cleanrot Knight's Sword",
                "order": 76,
                "upgrade": null,
                "infusion": "Heavy",
                "weaponArt": "Bloodhound's Step"
            },
            {
                "name": "Cleanrot Knight's Sword",
                "order": 77,
                "upgrade": null,
                "infusion": "Heavy",
                "weaponArt": "Bloodhound's Step"
            },
            {
                "name": "Cleanrot Knight's Sword",
                "order": 78,
                "upgrade": null,
                "infusion": "Heavy",
                "weaponArt": "Bloodhound's Step"
            },
            {
                "name": "Cleanrot Knight's Sword",
                "order": 79,
                "upgrade": null,
                "infusion": "Heavy",
                "weaponArt": "Bloodhound's Step"
            },
            {
                "name": "Sword Lance",
                "order": 80,
                "upgrade": null,
                "infusion": "Heavy",
                "weaponArt": "Storm Stomp"
            },
            {
                "name": "Sword Lance",
                "order": 81,
                "upgrade": null,
                "infusion": "Heavy",
                "weaponArt": "Raptor of the Mists"
            },
            {
                "name": "Great Katana",
                "order": 82,
                "upgrade": null,
                "infusion": "Heavy",
                "weaponArt": "Bloodhound's Step"
            },
            {
                "name": "Great Katana",
                "order": 83,
                "upgrade": null,
                "infusion": "Heavy",
                "weaponArt": "Quickstep"
            },
            {
                "name": "Milady",
                "order": 84,
                "upgrade": null,
                "infusion": "Heavy",
                "weaponArt": "Sword Dance"
            },
            {
                "name": "Dismounter",
                "order": 85,
                "upgrade": null,
                "infusion": "Heavy",
                "weaponArt": "Flaming Strike"
            },
            {
                "name": "Freyja's Greatsword",
                "order": 86,
                "upgrade": null,
                "infusion": "Heavy",
                "weaponArt": "Storm Stomp"
            },
            {
                "name": "Greatsword",
                "order": 87,
                "upgrade": null,
                "infusion": "Heavy",
                "weaponArt": "Storm Stomp"
            },
            {
                "name": "Greatsword",
                "order": 88,
                "upgrade": null,
                "infusion": "Heavy",
                "weaponArt": "Giant Hunt"
            },
            {
                "name": "Great Club",
                "order": 89,
                "upgrade": null,
                "infusion": "Standard",
                "weaponArt": null
            },
            {
                "name": "Cleanrot Knight's Sword",
                "order": 90,
                "upgrade": null,
                "infusion": "Heavy",
                "weaponArt": "Storm Stomp"
            },
            {
                "name": "Cleanrot Knight's Sword",
                "order": 91,
                "upgrade": null,
                "infusion": "Heavy",
                "weaponArt": "Quickstep"
            },
            {
                "name": "Cleanrot Knight's Sword",
                "order": 92,
                "upgrade": null,
                "infusion": "Heavy",
                "weaponArt": "Raptor of the Mists"
            },
            {
                "name": "Shamshir",
                "order": 93,
                "upgrade": null,
                "infusion": "Heavy",
                "weaponArt": "Quickstep"
            },
            {
                "name": "Executioner's Greataxe",
                "order": 94,
                "upgrade": null,
                "infusion": "Heavy",
                "weaponArt": "Braggart's Roar"
            },
            {
                "name": "Backhand Blade",
                "order": 95,
                "upgrade": null,
                "infusion": "Heavy",
                "weaponArt": "Bloodhound's Step"
            },
            {
                "name": "Mis\u00e9ricorde",
                "order": 96,
                "upgrade": null,
                "infusion": "Fire",
                "weaponArt": "Kick"
            },
            {
                "name": "Pata",
                "order": 97,
                "upgrade": null,
                "infusion": "Heavy",
                "weaponArt": "Endure"
            },
            {
                "name": "Venomous Fang",
                "order": 98,
                "upgrade": null,
                "infusion": "Heavy",
                "weaponArt": "Endure"
            },
            {
                "name": "Stone Club",
                "order": 99,
                "upgrade": null,
                "infusion": "Heavy",
                "weaponArt": "Endure"
            },
            {
                "name": "Rabbath's Cannon",
                "order": 100,
                "upgrade": null,
                "infusion": "Standard",
                "weaponArt": null
            },
            {
                "name": "Poisoned Hand",
                "order": 101,
                "upgrade": null,
                "infusion": "Standard",
                "weaponArt": null
            },
            {
                "name": "Frenzied Flame Seal",
                "order": 102,
                "upgrade": null,
                "equipSet": [
                    4
                ],
                "infusion": "Standard",
                "weaponArt": null,
                "equipIndex": 4
            },
            {
                "name": "Staff of Loss",
                "order": 103,
                "upgrade": null,
                "infusion": "Standard",
                "weaponArt": "Spinning Weapon"
            },
            {
                "name": "Brass Shield",
                "order": 104,
                "upgrade": null,
                "infusion": "Standard",
                "weaponArt": "No Skill"
            },
            {
                "name": "Fingerprint Stone Shield",
                "order": 105,
                "upgrade": null,
                "infusion": "Standard",
                "weaponArt": "No Skill"
            },
            {
                "name": "Carian Thrusting Shield",
                "order": 106,
                "upgrade": null,
                "infusion": "Heavy",
                "weaponArt": "Bloodhound's Step"
            },
            {
                "name": "Carian Thrusting Shield",
                "order": 107,
                "upgrade": null,
                "infusion": "Heavy",
                "weaponArt": "Giant Hunt"
            },
            {
                "name": "Carian Thrusting Shield",
                "order": 108,
                "upgrade": null,
                "infusion": "Heavy",
                "weaponArt": "Raptor of the Mists"
            },
            {
                "name": "Carian Thrusting Shield",
                "order": 109,
                "upgrade": null,
                "infusion": "Heavy",
                "weaponArt": "Storm Stomp"
            }
        ],
        "sorting": {
            "method": "acquisition",
            "direction": "asc"
        }
    },
    "talismans": {
        "slots": [
            {
                "name": "Red-Feathered Branchsword",
                "order": 0
            },
            {
                "name": "Red-Feathered Branchsword",
                "order": 1
            },
            {
                "name": "Red-Feathered Branchsword",
                "order": 2
            },
            {
                "name": "Red-Feathered Branchsword",
                "order": 3
            },
            {
                "name": "Red-Feathered Branchsword",
                "order": 4
            },
            {
                "name": "Great-Jar's Arsenal",
                "order": 5
            },
            {
                "name": "Stalwart Horn Charm +2",
                "order": 6
            },
            {
                "name": "Clarifying Horn Charm +2",
                "order": 7
            },
            {
                "name": "Ailment Talisman",
                "order": 8
            },
            {
                "name": "Erdtree's Favor +2",
                "order": 9
            },
            {
                "name": "Bull-Goat's Talisman",
                "order": 10
            },
            {
                "name": "Spear Talisman",
                "order": 11,
                "equipSet": [
                    1
                ],
                "equipIndex": 1
            },
            {
                "name": "Arrow's Soaring Sting Talisman",
                "order": 12
            },
            {
                "name": "Ritual Shield Talisman",
                "order": 13
            },
            {
                "name": "Two-Handed Sword Talisman",
                "order": 14,
                "equipSet": [
                    0
                ],
                "equipIndex": 0
            },
            {
                "name": "Rotten Winged Sword Insignia",
                "order": 15
            },
            {
                "name": "Crimson Amber Medallion +3",
                "order": 16
            },
            {
                "name": "Two-Headed Turtle Talisman",
                "order": 17
            },
            {
                "name": "Shard of Alexander",
                "order": 18
            },
            {
                "name": "Arrow's Sting Talisman",
                "order": 19
            },
            {
                "name": "Carian Filigreed Crest",
                "order": 20
            },
            {
                "name": "Lacerating Crossed-Tree",
                "order": 21,
                "equipSet": [
                    3
                ],
                "equipIndex": 3
            },
            {
                "name": "Claw Talisman",
                "order": 22
            },
            {
                "name": "Retaliatory Crossed-Tree",
                "order": 23,
                "equipSet": [
                    2
                ],
                "equipIndex": 2
            },
            {
                "name": "Two Fingers Heirloom",
                "order": 24
            },
            {
                "name": "Marika's Soreseal",
                "order": 25
            },
            {
                "name": "Dagger Talisman",
                "order": 26
            },
            {
                "name": "Kindred of Rot's Exultation",
                "order": 27
            },
            {
                "name": "Hammer Talisman",
                "order": 28
            },
            {
                "name": "Godskin Swaddling Cloth",
                "order": 29
            },
            {
                "name": "Crimson Seed Talisman +1",
                "order": 30
            },
            {
                "name": "Crimson Seed Talisman +1",
                "order": 31
            },
            {
                "name": "Crimson Seed Talisman +1",
                "order": 32
            },
            {
                "name": "Crimson Seed Talisman +1",
                "order": 33
            },
            {
                "name": "Crimson Seed Talisman +1",
                "order": 34
            },
            {
                "name": "Crimson Seed Talisman +1",
                "order": 35
            },
            {
                "name": "Crimson Seed Talisman +1",
                "order": 36
            },
            {
                "name": "Crimson Seed Talisman +1",
                "order": 37
            },
            {
                "name": "Crimson Seed Talisman +1",
                "order": 38
            },
            {
                "name": "Crimson Seed Talisman +1",
                "order": 39
            },
            {
                "name": "Crimson Seed Talisman +1",
                "order": 40
            },
            {
                "name": "Crimson Seed Talisman +1",
                "order": 41
            },
            {
                "name": "Crimson Seed Talisman +1",
                "order": 42
            },
            {
                "name": "Crimson Seed Talisman +1",
                "order": 43
            },
            {
                "name": "Crimson Seed Talisman +1",
                "order": 44
            },
            {
                "name": "Crimson Seed Talisman +1",
                "order": 45
            },
            {
                "name": "Crimson Seed Talisman +1",
                "order": 46
            },
            {
                "name": "Crimson Seed Talisman +1",
                "order": 47
            },
            {
                "name": "Crimson Seed Talisman +1",
                "order": 48
            },
            {
                "name": "Crimson Seed Talisman +1",
                "order": 49
            },
            {
                "name": "Crimson Seed Talisman +1",
                "order": 50
            },
            {
                "name": "Crimson Seed Talisman +1",
                "order": 51
            },
            {
                "name": "Crimson Seed Talisman +1",
                "order": 52
            },
            {
                "name": "Crimson Seed Talisman +1",
                "order": 53
            },
            {
                "name": "Crimson Seed Talisman +1",
                "order": 54
            },
            {
                "name": "Spelldrake Talisman +3",
                "order": 55
            },
            {
                "name": "Flamedrake Talisman +3",
                "order": 56
            },
            {
                "name": "Dragoncrest Greatshield Talisman",
                "order": 57
            },
            {
                "name": "Golden Braid",
                "order": 58
            },
            {
                "name": "Taker's Cameo",
                "order": 59
            },
            {
                "name": "Viridian Amber Medallion +3",
                "order": 60
            },
            {
                "name": "Blessed Blue Dew Talisman",
                "order": 61
            },
            {
                "name": "Companion Jar",
                "order": 62
            },
            {
                "name": "Blessed Dew Talisman",
                "order": 63
            },
            {
                "name": "Concealing Veil",
                "order": 64
            },
            {
                "name": "Blue-Feathered Branchsword",
                "order": 65
            },
            {
                "name": "Blue-Feathered Branchsword",
                "order": 66
            },
            {
                "name": "Blue-Feathered Branchsword",
                "order": 67
            },
            {
                "name": "Blue-Feathered Branchsword",
                "order": 68
            },
            {
                "name": "Blue-Feathered Branchsword",
                "order": 69
            }
        ],
        "sorting": {
            "method": "acquisition",
            "direction": "asc"
        }
    },
    "conditions": {
        "forEffects": [],
        "crystalTears": false
    },
    "protectors": {
        "arms": {
            "slots": [
                {
                    "name": "Royal Remains Gauntlets",
                    "order": 0
                },
                {
                    "name": "Royal Remains Gauntlets",
                    "order": 1
                },
                {
                    "name": "Royal Remains Gauntlets",
                    "order": 2
                },
                {
                    "name": "Royal Remains Gauntlets",
                    "order": 3
                },
                {
                    "name": "Royal Remains Gauntlets",
                    "order": 4
                },
                {
                    "name": "Briar Gauntlets",
                    "order": 5
                },
                {
                    "name": "Briar Gauntlets",
                    "order": 6
                },
                {
                    "name": "Briar Gauntlets",
                    "order": 7
                },
                {
                    "name": "Briar Gauntlets",
                    "order": 8
                },
                {
                    "name": "Briar Gauntlets",
                    "order": 9
                },
                {
                    "name": "Gauntlets of Solitude",
                    "order": 10
                },
                {
                    "name": "Verdigris Gauntlets",
                    "order": 11
                },
                {
                    "name": "Young Lion's Gauntlets",
                    "order": 12,
                    "equipSet": [
                        1
                    ],
                    "equipIndex": 1
                },
                {
                    "name": "Tree Sentinel Gauntlets",
                    "order": 13
                },
                {
                    "name": "Lionel's Gauntlets",
                    "order": 14
                }
            ],
            "sorting": {
                "method": "acquisition",
                "direction": "asc"
            }
        },
        "body": {
            "slots": [
                {
                    "name": "Guardian Garb (Full Bloom)",
                    "order": 0
                },
                {
                    "name": "Guardian Garb (Full Bloom)",
                    "order": 1
                },
                {
                    "name": "Guardian Garb (Full Bloom)",
                    "order": 2
                },
                {
                    "name": "Guardian Garb (Full Bloom)",
                    "order": 3
                },
                {
                    "name": "Guardian Garb (Full Bloom)",
                    "order": 4
                },
                {
                    "name": "Armor of Solitude",
                    "order": 5
                },
                {
                    "name": "Armor of Solitude",
                    "order": 6
                },
                {
                    "name": "Armor of Solitude",
                    "order": 7
                },
                {
                    "name": "Armor of Solitude",
                    "order": 8
                },
                {
                    "name": "Armor of Solitude",
                    "order": 9
                },
                {
                    "name": "Verdigris Armor",
                    "order": 10,
                    "equipSet": [
                        1
                    ],
                    "equipIndex": 1
                },
                {
                    "name": "Veteran's Armor",
                    "order": 11
                },
                {
                    "name": "Lionel's Armor",
                    "order": 12
                },
                {
                    "name": "Tree Sentinel Armor",
                    "order": 13
                },
                {
                    "name": "Fire Prelate Armor",
                    "order": 14
                }
            ],
            "sorting": {
                "method": "acquisition",
                "direction": "asc"
            }
        },
        "head": {
            "slots": [
                {
                    "name": "Crimson Tear Scarab",
                    "order": 0
                },
                {
                    "name": "Crimson Tear Scarab",
                    "order": 1
                },
                {
                    "name": "Crimson Tear Scarab",
                    "order": 2
                },
                {
                    "name": "Crimson Tear Scarab",
                    "order": 3
                },
                {
                    "name": "Crimson Tear Scarab",
                    "order": 4
                },
                {
                    "name": "Fire Knight Helm",
                    "order": 5
                },
                {
                    "name": "Fire Knight Helm",
                    "order": 6,
                    "equipSet": [
                        1
                    ],
                    "equipIndex": 1
                },
                {
                    "name": "Fire Knight Helm",
                    "order": 7
                },
                {
                    "name": "Fire Knight Helm",
                    "order": 8
                },
                {
                    "name": "Fire Knight Helm",
                    "order": 9
                },
                {
                    "name": "Mushroom Crown",
                    "order": 10
                },
                {
                    "name": "Mushroom Crown",
                    "order": 11
                },
                {
                    "name": "Mushroom Crown",
                    "order": 12
                },
                {
                    "name": "Mushroom Crown",
                    "order": 13
                },
                {
                    "name": "Mushroom Crown",
                    "order": 14
                },
                {
                    "name": "Shadow Militiaman Helm",
                    "order": 15
                },
                {
                    "name": "Verdigris Helm",
                    "order": 16
                },
                {
                    "name": "Veteran's Helm",
                    "order": 17
                },
                {
                    "name": "Lionel's Helm",
                    "order": 18
                },
                {
                    "name": "Winged Serpent Helm",
                    "order": 19
                }
            ],
            "sorting": {
                "method": "acquisition",
                "direction": "asc"
            }
        },
        "legs": {
            "slots": [
                {
                    "name": "Royal Remains Greaves",
                    "order": 0
                },
                {
                    "name": "Royal Remains Greaves",
                    "order": 1
                },
                {
                    "name": "Royal Remains Greaves",
                    "order": 2
                },
                {
                    "name": "Royal Remains Greaves",
                    "order": 3
                },
                {
                    "name": "Royal Remains Greaves",
                    "order": 4
                },
                {
                    "name": "Briar Greaves",
                    "order": 5
                },
                {
                    "name": "Briar Greaves",
                    "order": 6
                },
                {
                    "name": "Briar Greaves",
                    "order": 7
                },
                {
                    "name": "Briar Greaves",
                    "order": 8
                },
                {
                    "name": "Briar Greaves",
                    "order": 9
                },
                {
                    "name": "Verdigris Greaves",
                    "order": 10
                },
                {
                    "name": "Greaves of Solitude",
                    "order": 11
                },
                {
                    "name": "Tree Sentinel Greaves",
                    "order": 12,
                    "equipSet": [
                        1
                    ],
                    "equipIndex": 1
                },
                {
                    "name": "Lionel's Greaves",
                    "order": 13
                },
                {
                    "name": "Bull-Goat Greaves",
                    "order": 14
                }
            ],
            "sorting": {
                "method": "acquisition",
                "direction": "asc"
            }
        }
    },
    "weaponUpgrade": 25,
    "characterClass": "Vagabond"
}