{
    "id": "290567798944ed",
    "is2h": false,
    "name": "idfkman",
    "sets": {
        "weapons": [
            {
                "name": "Default",
                "active": true
            }
        ],
        "talismans": [
            {
                "name": "Default",
                "active": true
            }
        ],
        "protectors": [
            {
                "name": "Default",
                "active": true
            }
        ]
    },
    "tags": [
        "Dexterity",
        "DLC: SotE"
    ],
    "isPvE": false,
    "items": {
        "ammo": {
            "slots": []
        },
        "tools": {
            "slots": [],
            "sorting": {
                "method": "acquisition",
                "direction": "asc"
            }
        },
        "flasks": {
            "level": 12,
            "total": 14,
            "crimson": 10,
            "cerulean": 4
        },
        "crystalTears": [
            null,
            null
        ]
    },
    "stats": {
        "rl": 150,
        "arc": 0,
        "dex": 60,
        "fth": 19,
        "int": 0,
        "mnd": 10,
        "str": 20,
        "vig": 58,
        "vit": 46
    },
    "views": {
        "overview": "build-planner",
        "home/left": "Stats",
        "weapons-view/left": "Picker"
    },
    "spells": {
        "slots": []
    },
    "computed": {
        "maxFP": 78,
        "poise": {
            "altered": 101.33333308,
            "original": 76
        },
        "stats": {
            "arc": 1,
            "fth": 20,
            "int": 1
        },
        "defenses": {
            "fire": 187,
            "holy": 131,
            "magic": 131,
            "slash": 135,
            "pierce": 135,
            "strike": 135,
            "physical": 135,
            "lightning": 129
        },
        "maxHealth": 2572.625,
        "absorption": {
            "fire": 27.23475703000001,
            "holy": 25.581769687,
            "magic": 24.44138948800001,
            "slash": 32.39465167000001,
            "pierce": 31.892272789600007,
            "strike": 30.2992406542,
            "physical": 31.975464520000006,
            "lightning": 24.738881267199996
        },
        "maxStamina": 150,
        "resistances": {
            "focus": 300,
            "immunity": 330,
            "vitality": 259,
            "robustness": 349
        },
        "maxEquipLoad": 99.3657659
    },
    "greatRune": "Morgott's Great Rune",
    "inventory": {
        "slots": [
            {
                "name": "Spiralhorn Shield",
                "order": 0,
                "upgrade": null,
                "infusion": "Standard",
                "weaponArt": "No Skill"
            },
            {
                "name": "Serpent Crest Shield",
                "order": 1,
                "upgrade": null,
                "infusion": "Standard",
                "weaponArt": "Golden Parry"
            },
            {
                "name": "Serpent Crest Shield",
                "order": 2,
                "upgrade": null,
                "infusion": "Standard",
                "weaponArt": "No Skill"
            },
            {
                "name": "Serpent Crest Shield",
                "order": 3,
                "upgrade": null,
                "infusion": "Standard",
                "weaponArt": "Carian Retaliation"
            },
            {
                "name": "Twinbird Kite Shield",
                "order": 4,
                "upgrade": null,
                "infusion": "Standard",
                "weaponArt": "Holy Ground"
            },
            {
                "name": "Death Knight's Twin Axes",
                "order": 5,
                "upgrade": null,
                "infusion": "Standard",
                "weaponArt": null
            },
            {
                "name": "Death Knight's Twin Axes",
                "order": 6,
                "upgrade": null,
                "infusion": "Standard",
                "weaponArt": null
            },
            {
                "name": "Death Knight's Twin Axes",
                "order": 7,
                "upgrade": null,
                "infusion": "Standard",
                "weaponArt": null
            },
            {
                "name": "Death Knight's Twin Axes",
                "order": 8,
                "upgrade": null,
                "infusion": "Standard",
                "weaponArt": null
            },
            {
                "name": "Death Knight's Twin Axes",
                "order": 9,
                "upgrade": null,
                "infusion": "Standard",
                "weaponArt": null
            },
            {
                "name": "Godskin Stitcher",
                "order": 10,
                "upgrade": null,
                "infusion": "Lightning",
                "weaponArt": "Blinkbolt"
            },
            {
                "name": "Godskin Stitcher",
                "order": 11,
                "upgrade": null,
                "infusion": "Lightning",
                "weaponArt": "Blinkbolt"
            },
            {
                "name": "Godskin Stitcher",
                "order": 12,
                "upgrade": null,
                "infusion": "Lightning",
                "weaponArt": "Blinkbolt"
            },
            {
                "name": "Godskin Stitcher",
                "order": 13,
                "upgrade": null,
                "infusion": "Lightning",
                "weaponArt": "Blinkbolt"
            },
            {
                "name": "Godskin Stitcher",
                "order": 14,
                "upgrade": null,
                "infusion": "Lightning",
                "weaponArt": "Blinkbolt"
            },
            {
                "name": "Nightrider Flail",
                "order": 15,
                "upgrade": null,
                "infusion": "Lightning",
                "weaponArt": "Lightning Slash"
            },
            {
                "name": "Guardian's Swordspear",
                "order": 16,
                "upgrade": null,
                "infusion": "Keen",
                "weaponArt": "Spinning Slash"
            },
            {
                "name": "Rapier",
                "order": 17,
                "upgrade": null,
                "infusion": "Lightning",
                "weaponArt": "Quickstep"
            },
            {
                "name": "Banished Knight's Halberd",
                "order": 18,
                "upgrade": null,
                "infusion": "Keen",
                "weaponArt": "Spinning Slash"
            },
            {
                "name": "Zweihander",
                "order": 19,
                "upgrade": null,
                "infusion": "Lightning",
                "weaponArt": "Lightning Slash"
            },
            {
                "name": "Noble's Slender Sword",
                "order": 20,
                "upgrade": null,
                "infusion": "Lightning",
                "weaponArt": "Storm Stomp"
            },
            {
                "name": "Wakizashi",
                "order": 21,
                "upgrade": null,
                "infusion": "Keen",
                "weaponArt": "Impaling Thrust"
            },
            {
                "name": "Shamshir",
                "order": 22,
                "upgrade": null,
                "infusion": "Lightning",
                "weaponArt": "Parry"
            },
            {
                "name": "Great Knife",
                "order": 23,
                "upgrade": null,
                "infusion": "Standard",
                "weaponArt": "Storm Blade"
            },
            {
                "name": "Warhawk's Talon",
                "order": 24,
                "upgrade": null,
                "infusion": "Keen",
                "weaponArt": "Flaming Strike"
            },
            {
                "name": "Nagakiba",
                "order": 25,
                "upgrade": null,
                "infusion": "Lightning",
                "weaponArt": "Unsheathe"
            },
            {
                "name": "Backhand Blade",
                "order": 26,
                "upgrade": null,
                "infusion": "Lightning",
                "weaponArt": "Spinning Slash"
            },
            {
                "name": "Shamshir",
                "order": 27,
                "upgrade": null,
                "infusion": "Lightning",
                "weaponArt": "Kick"
            },
            {
                "name": "Great Katana",
                "order": 28,
                "upgrade": null,
                "infusion": "Standard",
                "weaponArt": "Piercing Fang"
            },
            {
                "name": "Sword of Night",
                "order": 29,
                "upgrade": null,
                "infusion": "Standard",
                "weaponArt": null
            },
            {
                "name": "Katar",
                "order": 30,
                "upgrade": null,
                "infusion": "Keen",
                "weaponArt": "Flaming Strike"
            },
            {
                "name": "Spiked Caestus",
                "order": 31,
                "upgrade": null,
                "infusion": "Keen",
                "weaponArt": "Storm Stomp"
            },
            {
                "name": "Cleanrot Knight's Sword",
                "order": 32,
                "upgrade": null,
                "infusion": "Keen",
                "weaponArt": "Bloodhound's Step"
            },
            {
                "name": "Raptor Talons",
                "order": 33,
                "upgrade": null,
                "infusion": "Keen",
                "weaponArt": "Endure"
            },
            {
                "name": "Urumi",
                "order": 34,
                "upgrade": null,
                "infusion": "Keen",
                "weaponArt": "Royal Knight's Resolve"
            },
            {
                "name": "Grave Scythe",
                "order": 35,
                "upgrade": null,
                "infusion": "Lightning",
                "weaponArt": "Kick"
            },
            {
                "name": "Leda's Sword",
                "order": 36,
                "upgrade": null,
                "infusion": "Standard",
                "weaponArt": null
            },
            {
                "name": "Eclipse Shotel",
                "order": 37,
                "upgrade": null,
                "infusion": "Standard",
                "weaponArt": null
            },
            {
                "name": "Greatbow",
                "order": 38,
                "upgrade": null,
                "infusion": "Standard",
                "weaponArt": "Rain of Arrows"
            },
            {
                "name": "Bone Bow",
                "order": 39,
                "upgrade": null,
                "infusion": "Standard",
                "weaponArt": null
            },
            {
                "name": "Greatsword of Damnation",
                "order": 40,
                "upgrade": null,
                "infusion": "Standard",
                "weaponArt": null
            },
            {
                "name": "Greatsword of Damnation",
                "order": 41,
                "upgrade": null,
                "infusion": "Standard",
                "weaponArt": null
            },
            {
                "name": "Greatsword of Damnation",
                "order": 42,
                "upgrade": null,
                "infusion": "Standard",
                "weaponArt": null
            },
            {
                "name": "Greatsword of Damnation",
                "order": 43,
                "upgrade": null,
                "infusion": "Standard",
                "weaponArt": null
            },
            {
                "name": "Greatsword of Damnation",
                "order": 44,
                "upgrade": null,
                "infusion": "Standard",
                "weaponArt": null
            },
            {
                "name": "Zamor Curved Sword",
                "order": 45,
                "upgrade": null,
                "infusion": "Standard",
                "weaponArt": null
            },
            {
                "name": "Zamor Curved Sword",
                "order": 46,
                "upgrade": null,
                "infusion": "Standard",
                "weaponArt": null
            },
            {
                "name": "Zamor Curved Sword",
                "order": 47,
                "upgrade": null,
                "infusion": "Standard",
                "weaponArt": null
            },
            {
                "name": "Zamor Curved Sword",
                "order": 48,
                "upgrade": null,
                "infusion": "Standard",
                "weaponArt": null
            },
            {
                "name": "Zamor Curved Sword",
                "order": 49,
                "upgrade": null,
                "infusion": "Standard",
                "weaponArt": null
            },
            {
                "name": "Noble's Slender Sword",
                "order": 50,
                "upgrade": null,
                "infusion": "Lightning",
                "weaponArt": "Thunderbolt"
            },
            {
                "name": "Wakizashi",
                "order": 51,
                "upgrade": null,
                "infusion": "Keen",
                "weaponArt": "Thunderbolt"
            },
            {
                "name": "Forked Hatchet",
                "order": 52,
                "upgrade": null,
                "infusion": "Lightning",
                "weaponArt": "Thunderbolt"
            },
            {
                "name": "Great Knife",
                "order": 53,
                "upgrade": null,
                "infusion": "Keen",
                "weaponArt": "Thunderbolt"
            },
            {
                "name": "Noble's Slender Sword",
                "order": 54,
                "upgrade": null,
                "infusion": "Lightning",
                "weaponArt": "Thunderbolt"
            },
            {
                "name": "Nagakiba",
                "order": 55,
                "upgrade": null,
                "infusion": "Lightning",
                "weaponArt": "Piercing Fang"
            },
            {
                "name": "Backhand Blade",
                "order": 56,
                "upgrade": null,
                "infusion": "Lightning",
                "weaponArt": "Thunderbolt"
            },
            {
                "name": "Backhand Blade",
                "order": 57,
                "upgrade": null,
                "infusion": "Lightning",
                "weaponArt": "Thunderbolt"
            },
            {
                "name": "Spiked Caestus",
                "order": 58,
                "upgrade": null,
                "infusion": "Keen",
                "weaponArt": "Endure"
            },
            {
                "name": "Katar",
                "order": 59,
                "upgrade": null,
                "infusion": "Keen",
                "weaponArt": "Thunderbolt"
            },
            {
                "name": "Mis\u00e9ricorde",
                "order": 60,
                "upgrade": null,
                "infusion": "Lightning",
                "weaponArt": "Endure"
            },
            {
                "name": "Mis\u00e9ricorde",
                "order": 61,
                "upgrade": null,
                "infusion": "Lightning",
                "weaponArt": "Endure"
            },
            {
                "name": "Mis\u00e9ricorde",
                "order": 62,
                "upgrade": null,
                "infusion": "Lightning",
                "weaponArt": "Endure"
            },
            {
                "name": "Mis\u00e9ricorde",
                "order": 63,
                "upgrade": null,
                "infusion": "Lightning",
                "weaponArt": "Endure"
            },
            {
                "name": "Mis\u00e9ricorde",
                "order": 64,
                "upgrade": null,
                "infusion": "Lightning",
                "weaponArt": "Endure"
            },
            {
                "name": "Mis\u00e9ricorde",
                "order": 65,
                "upgrade": null,
                "infusion": "Lightning",
                "weaponArt": "Bloodhound's Step"
            },
            {
                "name": "Mis\u00e9ricorde",
                "order": 66,
                "upgrade": null,
                "infusion": "Lightning",
                "weaponArt": "Bloodhound's Step"
            },
            {
                "name": "Mis\u00e9ricorde",
                "order": 67,
                "upgrade": null,
                "infusion": "Lightning",
                "weaponArt": "Bloodhound's Step"
            },
            {
                "name": "Mis\u00e9ricorde",
                "order": 68,
                "upgrade": null,
                "infusion": "Lightning",
                "weaponArt": "Bloodhound's Step"
            },
            {
                "name": "Mis\u00e9ricorde",
                "order": 69,
                "upgrade": null,
                "infusion": "Lightning",
                "weaponArt": "Bloodhound's Step"
            },
            {
                "name": "Pata",
                "order": 70,
                "upgrade": null,
                "infusion": "Keen",
                "weaponArt": "Endure"
            },
            {
                "name": "Pata",
                "order": 71,
                "upgrade": null,
                "infusion": "Keen",
                "weaponArt": "Endure"
            },
            {
                "name": "Pata",
                "order": 72,
                "upgrade": null,
                "infusion": "Keen",
                "weaponArt": "Endure"
            },
            {
                "name": "Pata",
                "order": 73,
                "upgrade": null,
                "infusion": "Keen",
                "weaponArt": "Endure"
            },
            {
                "name": "Pata",
                "order": 74,
                "upgrade": null,
                "infusion": "Keen",
                "weaponArt": "Endure"
            },
            {
                "name": "Pata",
                "order": 75,
                "upgrade": null,
                "infusion": "Keen",
                "weaponArt": "Bloodhound's Step"
            },
            {
                "name": "Pata",
                "order": 76,
                "upgrade": null,
                "infusion": "Keen",
                "weaponArt": "Bloodhound's Step"
            },
            {
                "name": "Pata",
                "order": 77,
                "upgrade": null,
                "infusion": "Keen",
                "weaponArt": "Bloodhound's Step"
            },
            {
                "name": "Pata",
                "order": 78,
                "upgrade": null,
                "infusion": "Keen",
                "weaponArt": "Bloodhound's Step"
            },
            {
                "name": "Pata",
                "order": 79,
                "upgrade": null,
                "infusion": "Keen",
                "weaponArt": "Bloodhound's Step"
            },
            {
                "name": "Star Fist",
                "order": 80,
                "upgrade": null,
                "infusion": "Keen",
                "weaponArt": "Endure"
            },
            {
                "name": "Star Fist",
                "order": 81,
                "upgrade": null,
                "infusion": "Keen",
                "weaponArt": "Endure"
            },
            {
                "name": "Star Fist",
                "order": 82,
                "upgrade": null,
                "infusion": "Keen",
                "weaponArt": "Endure"
            },
            {
                "name": "Star Fist",
                "order": 83,
                "upgrade": null,
                "infusion": "Keen",
                "weaponArt": "Endure"
            },
            {
                "name": "Star Fist",
                "order": 84,
                "upgrade": null,
                "infusion": "Keen",
                "weaponArt": "Endure"
            },
            {
                "name": "Star Fist",
                "order": 85,
                "upgrade": null,
                "infusion": "Keen",
                "weaponArt": "Endure"
            },
            {
                "name": "Star Fist",
                "order": 86,
                "upgrade": null,
                "infusion": "Keen",
                "weaponArt": "Endure"
            },
            {
                "name": "Star Fist",
                "order": 87,
                "upgrade": null,
                "infusion": "Keen",
                "weaponArt": "Endure"
            },
            {
                "name": "Star Fist",
                "order": 88,
                "upgrade": null,
                "infusion": "Keen",
                "weaponArt": "Endure"
            },
            {
                "name": "Star Fist",
                "order": 89,
                "upgrade": null,
                "infusion": "Keen",
                "weaponArt": "Endure"
            },
            {
                "name": "Icon Shield",
                "order": 90,
                "upgrade": null,
                "infusion": "Standard",
                "weaponArt": null
            },
            {
                "name": "Icon Shield",
                "order": 91,
                "upgrade": null,
                "infusion": "Standard",
                "weaponArt": null
            },
            {
                "name": "Icon Shield",
                "order": 92,
                "upgrade": null,
                "infusion": "Standard",
                "weaponArt": null
            },
            {
                "name": "Icon Shield",
                "order": 93,
                "upgrade": null,
                "infusion": "Standard",
                "weaponArt": null
            },
            {
                "name": "Icon Shield",
                "order": 94,
                "upgrade": null,
                "infusion": "Standard",
                "weaponArt": null
            }
        ],
        "sorting": {
            "method": "acquisition",
            "direction": "asc"
        }
    },
    "talismans": {
        "slots": [
            {
                "name": "Crucible Knot Talisman",
                "order": 0
            },
            {
                "name": "Red-Feathered Branchsword",
                "order": 1
            },
            {
                "name": "Blue-Feathered Branchsword",
                "order": 2
            },
            {
                "name": "Lacerating Crossed-Tree",
                "order": 3
            },
            {
                "name": "Retaliatory Crossed-Tree",
                "order": 4
            },
            {
                "name": "Two-Headed Turtle Talisman",
                "order": 5,
                "equipSet": [
                    3
                ],
                "equipIndex": 3
            },
            {
                "name": "Axe Talisman",
                "order": 6
            },
            {
                "name": "Spear Talisman",
                "order": 7
            },
            {
                "name": "Godskin Swaddling Cloth",
                "order": 8
            },
            {
                "name": "Hammer Talisman",
                "order": 9
            },
            {
                "name": "Immunizing Horn Charm +2",
                "order": 10
            },
            {
                "name": "Dagger Talisman",
                "order": 11
            },
            {
                "name": "Ritual Shield Talisman",
                "order": 12,
                "equipSet": [
                    2
                ],
                "equipIndex": 2
            },
            {
                "name": "Rotten Winged Sword Insignia",
                "order": 13
            },
            {
                "name": "Two Fingers Heirloom",
                "order": 14
            },
            {
                "name": "Clarifying Horn Charm +2",
                "order": 15
            },
            {
                "name": "Shard of Alexander",
                "order": 16
            },
            {
                "name": "Erdtree's Favor +2",
                "order": 17
            },
            {
                "name": "Millicent's Prosthesis",
                "order": 18
            },
            {
                "name": "Bull-Goat's Talisman",
                "order": 19,
                "equipSet": [
                    0
                ],
                "equipIndex": 0
            },
            {
                "name": "Stalwart Horn Charm +2",
                "order": 20
            },
            {
                "name": "Great-Jar's Arsenal",
                "order": 21
            },
            {
                "name": "Crimson Amber Medallion +3",
                "order": 22,
                "equipSet": [
                    1
                ],
                "equipIndex": 1
            },
            {
                "name": "Two-Handed Sword Talisman",
                "order": 23
            },
            {
                "name": "Crimson Seed Talisman +1",
                "order": 24
            },
            {
                "name": "Blessed Dew Talisman",
                "order": 25
            },
            {
                "name": "Blessed Blue Dew Talisman",
                "order": 26
            },
            {
                "name": "Rellana's Cameo",
                "order": 27
            },
            {
                "name": "Marika's Soreseal",
                "order": 28
            }
        ],
        "sorting": {
            "method": "acquisition",
            "direction": "asc"
        }
    },
    "conditions": {
        "forEffects": [],
        "crystalTears": false
    },
    "protectors": {
        "arms": {
            "slots": [
                {
                    "name": "Fire Prelate Gauntlets",
                    "order": 0,
                    "equipSet": [
                        1
                    ],
                    "equipIndex": 1
                }
            ],
            "sorting": {
                "method": "acquisition",
                "direction": "asc"
            }
        },
        "body": {
            "slots": [
                {
                    "name": "Beast Champion Armor",
                    "order": 0,
                    "equipSet": [
                        1
                    ],
                    "equipIndex": 1
                }
            ],
            "sorting": {
                "method": "acquisition",
                "direction": "asc"
            }
        },
        "head": {
            "slots": [
                {
                    "name": "Circlet of Light",
                    "order": 0,
                    "equipSet": [
                        1
                    ],
                    "equipIndex": 1
                }
            ],
            "sorting": {
                "method": "acquisition",
                "direction": "asc"
            }
        },
        "legs": {
            "slots": [
                {
                    "name": "Greaves of Solitude",
                    "order": 0,
                    "equipSet": [
                        1
                    ],
                    "equipIndex": 1
                }
            ],
            "sorting": {
                "method": "acquisition",
                "direction": "asc"
            }
        }
    },
    "weaponUpgrade": 25,
    "characterClass": null
}